{
  "site": {
    "description": "验证网站的基础 URL (不带 /verify)",
    "type": "string",
    "default": "http://example.com"
  },
  "encsec": {
    "description": "接口通信所需的 encsec 密钥",
    "type": "string",
    "default": "your_secret_key"
  },
  "timeout_admin_id": {
    "description": "超时未验证时，需要被 @ 的管理员 QQ 号",
    "type": "string",
    "default": "123456789"
  },
  "extra_admins": {
    "description": "额外的管理员 QQ 号列表 (允许强制通过)",
    "type": "list",
    "items": {
      "type": "string"
    },
    "default": []
  }
}